predeq/__init__.py
predeq/_predeq.py
predeq/recipes.py
predeq-0.0.3.dist-info/METADATA
predeq-0.0.3.dist-info/WHEEL
predeq-0.0.3.dist-info/licenses/LICENSE
predeq-0.0.3.dist-info/RECORD
