Metadata-Version: 2.3
Name: predeq
Version: 0.0.3
Summary: Predicate-based equivalence testing
Project-URL: Homepage, https://github.com/petuzk/predeq
Author-email: Taras Radchenko <petuzk.dev@gmail.com>
License-Expression: MIT
License-File: LICENSE
Classifier: License :: OSI Approved :: MIT License
Classifier: Operating System :: OS Independent
Classifier: Programming Language :: Python :: 3
Classifier: Topic :: Software Development :: Testing
Requires-Python: >=3.8
Provides-Extra: dev
Requires-Dist: pytest; extra == 'dev'
